scscope/__init__.py
scscope/large_scale_processing.py
scscope/ops.py
scScope-0.1.5.dist-info/LICENSE
scScope-0.1.5.dist-info/METADATA
scScope-0.1.5.dist-info/WHEEL
scScope-0.1.5.dist-info/top_level.txt
scScope-0.1.5.dist-info/RECORD
